<?xml version="1.0" encoding="utf-8"?>
<!--Generated with LocalizationBuddy.-->
<!--Copyright Firaxis Games 2010-->
<!--All Rights Reserved-->
<GameData>
  <Language_IT_IT>
    <Row Tag="TXT_KEY_PROMOTION_SKI_INFANTRY">
      <Text>Bonus in Neve, Tundra e Collina</Text>
    </Row>
    <Row Tag="TXT_KEY_PROMOTION_SKI_INFANTRY_HELP">
      <Text>In caselle di Neve, Tundra o Collina: bonus al combattimento del 25% (se non è presente Foresta o Giungla) e movimento raddoppiato</Text>
    </Row>
    <Row Tag="TXT_KEY_UNIT_DANISH_BERSERKER">
      <Text>Berserker|un Berserker|dal tuo Berserker|al tuo Berserker|il tuo Berserker|da un Berserker</Text>
      <Gender>masculine</Gender>
      <Plurality>1</Plurality>
    </Row>
    <Row Tag="TXT_KEY_UNIT_DANISH_SKI_INFANTRY">
      <Text>Fanteria norvegese sugli sci|una Fanteria norvegese sugli sci|dalla tua Fanteria norvegese sugli sci|alla tua Fanteria norvegese sugli sci|la tua Fanteria norvegese sugli sci|da una Fanteria norvegese sugli sci</Text>
      <Gender>feminine</Gender>
      <Plurality>1</Plurality>
    </Row>
  </Language_IT_IT>
</GameData>