<?xml version="1.0" encoding="utf-8"?>
<!--Generated with LocalizationBuddy.-->
<!--Copyright Firaxis Games 2010-->
<!--All Rights Reserved-->
<GameData>
  <Language_ES_ES>
    <Row Tag="TXT_KEY_SCRAMBLE_AFRICA_CIV_AMERICA_ADJECTIVE">
      <Text>bóer|bóer|bóers|bóers</Text>
      <Gender>masculine|feminine|masculine|feminine</Gender>
      <Plurality>1|1|2|2</Plurality>
    </Row>
    <Row Tag="TXT_KEY_SCRAMBLE_AFRICA_CIV_AMERICA_DESC">
      <Text>Provincia del Cabo</Text>
      <Gender>feminine</Gender>
      <Plurality>1</Plurality>
    </Row>
    <Row Tag="TXT_KEY_SCRAMBLE_AFRICA_CIV_AMERICA_SHORT_DESC">
      <Text>Bóers</Text>
      <Gender>masculine</Gender>
      <Plurality>2</Plurality>
    </Row>
    <Row Tag="TXT_KEY_SCRAMBLE_AFRICA_CIV_BRAZIL_ADJECTIVE">
      <Text>belga|belga|belgas|belgas</Text>
      <Gender>masculine|feminine|masculine|feminine</Gender>
      <Plurality>1|1|2|2</Plurality>
    </Row>
    <Row Tag="TXT_KEY_SCRAMBLE_AFRICA_CIV_BRAZIL_DESC">
      <Text>Bélgica</Text>
      <Gender>feminine</Gender>
      <Plurality>1</Plurality>
    </Row>
    <Row Tag="TXT_KEY_SCRAMBLE_AFRICA_CIV_BRAZIL_SHORT_DESC">
      <Text>Bélgica</Text>
      <Gender>feminine</Gender>
      <Plurality>1</Plurality>
    </Row>
    <Row Tag="TXT_KEY_SCRAMBLE_AFRICA_CIV_ROME_ADJECTIVE">
      <Text>italiano|italiana|italianos|italianas</Text>
      <Gender>masculine|feminine|masculine|feminine</Gender>
      <Plurality>1|1|2|2</Plurality>
    </Row>
    <Row Tag="TXT_KEY_SCRAMBLE_AFRICA_CIV_ROME_DESC">
      <Text>Italia</Text>
      <Gender>feminine</Gender>
      <Plurality>1</Plurality>
    </Row>
    <Row Tag="TXT_KEY_SCRAMBLE_AFRICA_CIV_ROME_SHORT_DESC">
      <Text>Italia</Text>
      <Gender>feminine</Gender>
      <Plurality>1</Plurality>
    </Row>
  </Language_ES_ES>
</GameData>