<?xml version="1.0" encoding="utf-8"?>
<!--Generated with LocalizationBuddy.-->
<!--Copyright Firaxis Games 2010-->
<!--All Rights Reserved-->
<GameData>
  <Language_FR_FR>
    <Row Tag="TXT_KEY_CIV5_ANASAZI_TEXT">
      <Text>Les Anasazis sont une ancienne culture indigène, et les ancêtres des Indiens Pueblos actuels. Ils sont connus pour avoir construit des habitations troglodytes sous les falaises du canyon de Mesa Verde.</Text>
    </Row>
    <Row Tag="TXT_KEY_CIV5_NEWWORLD_SCENARIO_CONQUISTADOR_HELP">
      <Text>Unité de la Renaissance spécialisée dans l'exploration et la colonisation par-delà les mers. Elle peut être produite par toutes les civilisations.</Text>
    </Row>
    <Row Tag="TXT_KEY_CIV5_NEWWORLD_SCENARIO_CONQUISTADOR_STRATEGY">
      <Text>Le conquistador est une unité polyvalente aussi puissante sur terre que sur mer. Il remplace le chevalier et fait preuve de véritables talents d'exploration sur terre grâce à son champ de vision amélioré et la possibilité de fonder des villes. Sur l'eau, la promotion "Embarcation défensive" lui permet de se défendre contre les unités navales. À la différence du chevalier, il ne reçoit aucune pénalité lors de l'attaque de villes.</Text>
    </Row>
    <Row Tag="TXT_KEY_CIV5_NEWWORLD_SCENARIO_MUSKETEER_HELP">
      <Text>Cette unité est plus [ICON_STRENGTH] puissante en combat que l'arquebusier, ce qui en fait la plus puissante unité de combat rapproché du jeu. Elle peut être produite par toutes les civilisations.</Text>
    </Row>
    <Row Tag="TXT_KEY_CIV5_NEWWORLD_SCENARIO_MUSKETEER_STRATEGY">
      <Text>Le mousquetaire est nettement plus puissant que l'arquebusier, ce qui en fait le fantassin le plus redoutable du jeu.</Text>
    </Row>
    <Row Tag="TXT_KEY_CIV5_NEWWORLD_SCENARIO_TERCIO_HELP">
      <Text>Unité militaire dominante de la Renaissance. Cette unité est très [ICON_STRENGTH] puissante en combat, et dispose de la promotion "Bonus contre les unités montées (100)". Elle peut être produite par toutes les civilisations.</Text>
    </Row>
    <Row Tag="TXT_KEY_CIV5_NEWWORLD_SCENARIO_TERCIO_STRATEGY">
      <Text>Cette unité est plus puissante en combat que l'arquebusier, et sa puissance est doublée contre les unités montées.</Text>
    </Row>
    <Row Tag="TXT_KEY_NEWWORLD_SCENARIO_ABLTY_DECLARE_WAR_ALL">
      <Text>Permet de déclarer la guerre à n'importe quelle puissance.</Text>
    </Row>
    <Row Tag="TXT_KEY_NEWWORLD_SCENARIO_BRIEFING">
      <Text>Info</Text>
    </Row>
    <Row Tag="TXT_KEY_NEWWORLD_SCENARIO_BUILDING_MONASTERY_HELP">
      <Text>Le coût en [ICON_CULTURE] culture pour l'achat de nouvelles cases diminue de 75% dans toutes les villes.</Text>
    </Row>
    <Row Tag="TXT_KEY_NEWWORLD_SCENARIO_BUILDING_MONASTERY_STRATEGY">
      <Text>Le monastère augmente la [ICON_CULTURE] culture d'une ville, en accélérant la croissance de son territoire et l'acquisition par la civilisation de nouvelles doctrines sociales. Le monastère multiplie par quatre la vitesse d'expansion des frontières culturelles de la ville.</Text>
    </Row>
    <Row Tag="TXT_KEY_NEWWORLD_SCENARIO_BUILDING_NAVIGATION_SCHOOL">
      <Text>École de Navigation</Text>
    </Row>
    <Row Tag="TXT_KEY_NEWWORLD_SCENARIO_BUILDING_NAVIGATION_SCHOOL_HELP">
      <Text>Guérit le scorbut chez toutes les unités navales produites par l'empire.</Text>
    </Row>
    <Row Tag="TXT_KEY_NEWWORLD_SCENARIO_BUILDING_NAVIGATION_SCHOOL_STRATEGY">
      <Text>Construisez l'École de Navigation, une merveille nationale, et toutes vos unités navales à venir seront insensibles à la promotion "Scorbut".</Text>
    </Row>
    <Row Tag="TXT_KEY_NEWWORLD_SCENARIO_BUILDING_NAVIGATION_SCHOOL_TEXT">
      <Text>Les cartographes, constructeurs navals, et autres capitaines de frégate n'apparaissent pas comme par enchantement ; la plupart de ces érudits et nobles travailleurs ont reçu une formation au sein d'instituts comme les Écoles de Navigation. Des marins expérimentés et des professeurs émérites y partageaient leurs connaissances, et faisaient ainsi profiter des navigateurs en herbe de leur expérience. On dressait le tableau du climat attendu sur les nouvelles routes, on enseignait aux cartographes le maniement d'instruments dernier cri, et on concevait et construisait de nouveaux types de navires. [NEWLINE][NEWLINE]On raconte souvent qu'Henri le Navigateur, un prince du Portugal, a ouvert les portes de la première École de Navigation dans sa villa, à Sagres. Même s'il est vrai qu'il y avait réuni un groupe de cartographes pour étudier certaines côtes africaines, personne n'a jamais pu prouver l'existence d'une école centralisée pour les navigateurs et les érudits.
      </Text>
    </Row>
    <Row Tag="TXT_KEY_NEWWORLD_SCENARIO_CARAVEL_CARTIER">
      <Text>Cartier</Text>
    </Row>
    <Row Tag="TXT_KEY_NEWWORLD_SCENARIO_CARAVEL_CHAMPLAIN">
      <Text>Champlain</Text>
    </Row>
    <Row Tag="TXT_KEY_NEWWORLD_SCENARIO_CARAVEL_CHANCELLOR">
      <Text>Chancellor</Text>
    </Row>
    <Row Tag="TXT_KEY_NEWWORLD_SCENARIO_CARAVEL_DE_LEON">
      <Text>De León</Text>
    </Row>
    <Row Tag="TXT_KEY_NEWWORLD_SCENARIO_CARAVEL_DE_SOTO">
      <Text>De Soto</Text>
    </Row>
    <Row Tag="TXT_KEY_NEWWORLD_SCENARIO_CARAVEL_DE_VACA">
      <Text>De Vaca</Text>
    </Row>
    <Row Tag="TXT_KEY_NEWWORLD_SCENARIO_CARAVEL_GRENVILLE">
      <Text>Grenville</Text>
    </Row>
    <Row Tag="TXT_KEY_NEWWORLD_SCENARIO_CARAVEL_HUDSON">
      <Text>Hudson</Text>
    </Row>
    <Row Tag="TXT_KEY_NEWWORLD_SCENARIO_CARAVEL_MAGELLAN">
      <Text>Magellan</Text>
    </Row>
    <Row Tag="TXT_KEY_NEWWORLD_SCENARIO_CARAVEL_NARVAEZ">
      <Text>Narváez</Text>
    </Row>
    <Row Tag="TXT_KEY_NEWWORLD_SCENARIO_CARAVEL_ROBERVAL">
      <Text>Roberval</Text>
    </Row>
    <Row Tag="TXT_KEY_NEWWORLD_SCENARIO_CARAVEL_RUT">
      <Text>Rut</Text>
    </Row>
    <Row Tag="TXT_KEY_NEWWORLD_SCENARIO_CARAVEL_ULLOA">
      <Text>Ulloa</Text>
    </Row>
    <Row Tag="TXT_KEY_NEWWORLD_SCENARIO_CARAVEL_VESPUCCI">
      <Text>Vespucci</Text>
    </Row>
    <Row Tag="TXT_KEY_NEWWORLD_SCENARIO_CARAVEL_WILLOUGHBY">
      <Text>Willoughby</Text>
    </Row>
    <Row Tag="TXT_KEY_NEWWORLD_SCENARIO_CIV5_ALGONQUIN_TEXT">
      <Text>Les Algonquins sont un peuple autochtone du Québec. Leurs principaux rivaux étaient les Iroquois, leurs concurrents directs pour le commerce de la fourrure.</Text>
    </Row>
    <Row Tag="TXT_KEY_NEWWORLD_SCENARIO_CIV5_ARAWAK_TEXT">
      <Text>Les Arawaks sont un peuple autochtone des Indes occidentales. Ce sont les premiers indigènes rencontrés par Christophe Colomb.</Text>
    </Row>
    <Row Tag="TXT_KEY_NEWWORLD_SCENARIO_CIV5_CARIB_TEXT">
      <Text>Les Caraïbes sont l'un des peuples autochtones des Indes occidentales. Ils sont parmi les premiers à avoir combattu les Espagnols.</Text>
    </Row>
    <Row Tag="TXT_KEY_NEWWORLD_SCENARIO_CIV5_CHEROKEE_TEXT">
      <Text>Les Cherokees sont une tribu indigène originaire du sud-est des États-Unis. Ce sont des parents proches des Iroquois, c'est pourquoi on pense qu'ils ont émigré vers le sud depuis les Grands Lacs à la préhistoire.</Text>
    </Row>
    <Row Tag="TXT_KEY_NEWWORLD_SCENARIO_CIV5_DAWN_AZTECS_TEXT">
      <Text>
DESCRIPTION DU SCÉNARIO[NEWLINE]Nous sommes en 1492. Désireux de traverser l'Atlantique à la recherche d'une route menant jusqu'à la Chine et aux Indes, des explorateurs courtisent les cours d'Angleterre, de France et d'Espagne. Découvriront-ils une route commerciale et la richesse vers les côtes d'Asie ? Ou échoueront-ils sur des terres inconnues ? Les autochtones seront-ils réceptifs et accueillants, ou les repousseront-ils par la force ? Quelles richesses, quelle gloire et quelles opportunités attendent ces navigateurs ? Quel chemin choisirez-vous ? Qui remportera le combat pour la domination du Nouveau Monde ? [NEWLINE][NEWLINE]CONDITIONS DE VICTOIRE[NEWLINE]La victoire revient à la première civilisation qui atteint le score de 1000 points. Vous marquez des points lorsque vous atteignez la Chine en caravelle et lorsque vos unités de la Flotte des Indes rejoignent votre capitale. Jouez autant de fois que vous voulez en essayant les six civilisations : la carte de l'Amérique change à chaque partie. [NEWLINE][NEWLINE]RÈGLES SPÉCIALES[NEWLINE]Toutes les unités navales sont atteintes du scorbut, une "promotion" qui peut leur faire perdre des points de santé dès lors qu'elles terminent un tour en dehors des frontières de l'empire. Construisez l'École de Navigation, une merveille nationale, pour combattre cette maladie. Les puissances européennes ne peuvent pas se déclarer la guerre tant que l'une d'entre elles n'a pas découvert la technologie de la piraterie. Les unités de la Flotte des Indes sont créées lorsque des villes sont rasées ou en découvrant l'Eldorado et la montagne de Potosí, deux merveilles naturelles (si générées sur cette carte). Faites voyager ces unités jusqu'à votre capitale pour gagner de l'or et des points de victoire.</Text>
    </Row>
    <Row Tag="TXT_KEY_NEWWORLD_SCENARIO_CIV5_DAWN_ENGLAND_TEXT">
      <Text>
DESCRIPTION DU SCÉNARIO[NEWLINE]Nous sommes en 1492. Désireux de traverser l'Atlantique à la recherche d'une route menant jusqu'à la Chine et aux Indes, des explorateurs courtisent les cours d'Angleterre, de France et d'Espagne. Découvriront-ils une route commerciale et la richesse vers les côtes d'Asie ? Ou échoueront-ils sur des terres inconnues ? Les autochtones seront-ils réceptifs et accueillants, ou les repousseront-ils par la force ? Quelles richesses, quelle gloire et quelles opportunités attendent ces navigateurs ? Quel chemin choisirez-vous ? Qui remportera le combat pour la domination du Nouveau Monde ? [NEWLINE][NEWLINE]CONDITIONS DE VICTOIRE[NEWLINE]La victoire revient à la première civilisation qui atteint le score de 1000 points. Vous marquez des points lorsque vous atteignez la Chine en caravelle et lorsque vos unités de la Flotte des Indes rejoignent votre capitale. Jouez autant de fois que vous voulez en essayant les six civilisations : la carte de l'Amérique change à chaque partie. [NEWLINE][NEWLINE]RÈGLES SPÉCIALES[NEWLINE]Toutes les unités navales sont atteintes du scorbut, une "promotion" qui peut leur faire perdre des points de santé dès lors qu'elles terminent un tour en dehors des frontières de l'empire. Construisez l'École de Navigation, une merveille nationale, pour combattre cette maladie. Les puissances européennes ne peuvent pas se déclarer la guerre tant que l'une d'entre elles n'a pas découvert la technologie de la piraterie. Les unités de la Flotte des Indes sont créées lorsque des villes sont rasées ou en découvrant l'Eldorado et la montagne de Potosí, deux merveilles naturelles (si générées sur cette carte). Faites voyager ces unités jusqu'à votre capitale pour gagner de l'or et des points de victoire.</Text>
    </Row>
    <Row Tag="TXT_KEY_NEWWORLD_SCENARIO_CIV5_DAWN_FRANCE_TEXT">
      <Text>
DESCRIPTION DU SCÉNARIO[NEWLINE]Nous sommes en 1492. Désireux de traverser l'Atlantique à la recherche d'une route menant jusqu'à la Chine et aux Indes, des explorateurs courtisent les cours d'Angleterre, de France et d'Espagne. Découvriront-ils une route commerciale et la richesse vers les côtes d'Asie ? Ou échoueront-ils sur des terres inconnues ? Les autochtones seront-ils réceptifs et accueillants, ou les repousseront-ils par la force ? Quelles richesses, quelle gloire et quelles opportunités attendent ces navigateurs ? Quel chemin choisirez-vous ? Qui remportera le combat pour la domination du Nouveau Monde ? [NEWLINE][NEWLINE]CONDITIONS DE VICTOIRE[NEWLINE]La victoire revient à la première civilisation qui atteint le score de 1000 points. Vous marquez des points lorsque vous atteignez la Chine en caravelle et lorsque vos unités de la Flotte des Indes rejoignent votre capitale. Jouez autant de fois que vous voulez en essayant les six civilisations : la carte de l'Amérique change à chaque partie. [NEWLINE][NEWLINE]RÈGLES SPÉCIALES[NEWLINE]Toutes les unités navales sont atteintes du scorbut, une "promotion" qui peut leur faire perdre des points de santé dès lors qu'elles terminent un tour en dehors des frontières de l'empire. Construisez l'École de Navigation, une merveille nationale, pour combattre cette maladie. Les puissances européennes ne peuvent pas se déclarer la guerre tant que l'une d'entre elles n'a pas découvert la technologie de la piraterie. Les unités de la Flotte des Indes sont créées lorsque des villes sont rasées ou en découvrant l'Eldorado et la montagne de Potosí, deux merveilles naturelles (si générées sur cette carte). Faites voyager ces unités jusqu'à votre capitale pour gagner de l'or et des points de victoire.</Text>
    </Row>
    <Row Tag="TXT_KEY_NEWWORLD_SCENARIO_CIV5_DAWN_INCA_TEXT">
      <Text>
DESCRIPTION DU SCÉNARIO[NEWLINE]Nous sommes en 1492. Désireux de traverser l'Atlantique à la recherche d'une route menant jusqu'à la Chine et aux Indes, des explorateurs courtisent les cours d'Angleterre, de France et d'Espagne. Découvriront-ils une route commerciale et la richesse vers les côtes d'Asie ? Ou échoueront-ils sur des terres inconnues ? Les autochtones seront-ils réceptifs et accueillants, ou les repousseront-ils par la force ? Quelles richesses, quelle gloire et quelles opportunités attendent ces navigateurs ? Quel chemin choisirez-vous ? Qui remportera le combat pour la domination du Nouveau Monde ? [NEWLINE][NEWLINE]CONDITIONS DE VICTOIRE[NEWLINE]La victoire revient à la première civilisation qui atteint le score de 1000 points. Vous marquez des points lorsque vous atteignez la Chine en caravelle et lorsque vos unités de la Flotte des Indes rejoignent votre capitale. Jouez autant de fois que vous voulez en essayant les six civilisations : la carte de l'Amérique change à chaque partie. [NEWLINE][NEWLINE]RÈGLES SPÉCIALES[NEWLINE]Toutes les unités navales sont atteintes du scorbut, une "promotion" qui peut leur faire perdre des points de santé dès lors qu'elles terminent un tour en dehors des frontières de l'empire. Construisez l'École de Navigation, une merveille nationale, pour combattre cette maladie. Les puissances européennes ne peuvent pas se déclarer la guerre tant que l'une d'entre elles n'a pas découvert la technologie de la piraterie. Les unités de la Flotte des Indes sont créées lorsque des villes sont rasées ou en découvrant l'Eldorado et la montagne de Potosí, deux merveilles naturelles (si générées sur cette carte). Faites voyager ces unités jusqu'à votre capitale pour gagner de l'or et des points de victoire.</Text>
    </Row>
    <Row Tag="TXT_KEY_NEWWORLD_SCENARIO_CIV5_DAWN_IROQUOIS_TEXT">
      <Text>
DESCRIPTION DU SCÉNARIO[NEWLINE]Nous sommes en 1492. Désireux de traverser l'Atlantique à la recherche d'une route menant jusqu'à la Chine et aux Indes, des explorateurs courtisent les cours d'Angleterre, de France et d'Espagne. Découvriront-ils une route commerciale et la richesse vers les côtes d'Asie ? Ou échoueront-ils sur des terres inconnues ? Les autochtones seront-ils réceptifs et accueillants, ou les repousseront-ils par la force ? Quelles richesses, quelle gloire et quelles opportunités attendent ces navigateurs ? Quel chemin choisirez-vous ? Qui remportera le combat pour la domination du Nouveau Monde ? [NEWLINE][NEWLINE]CONDITIONS DE VICTOIRE[NEWLINE]La victoire revient à la première civilisation qui atteint le score de 1000 points. Vous marquez des points lorsque vous atteignez la Chine en caravelle et lorsque vos unités de la Flotte des Indes rejoignent votre capitale. Jouez autant de fois que vous voulez en essayant les six civilisations : la carte de l'Amérique change à chaque partie. [NEWLINE][NEWLINE]RÈGLES SPÉCIALES[NEWLINE]Toutes les unités navales sont atteintes du scorbut, une "promotion" qui peut leur faire perdre des points de santé dès lors qu'elles terminent un tour en dehors des frontières de l'empire. Construisez l'École de Navigation, une merveille nationale, pour combattre cette maladie. Les puissances européennes ne peuvent pas se déclarer la guerre tant que l'une d'entre elles n'a pas découvert la technologie de la piraterie. Les unités de la Flotte des Indes sont créées lorsque des villes sont rasées ou en découvrant l'Eldorado et la montagne de Potosí, deux merveilles naturelles (si générées sur cette carte). Faites voyager ces unités jusqu'à votre capitale pour gagner de l'or et des points de victoire.</Text>
    </Row>
    <Row Tag="TXT_KEY_NEWWORLD_SCENARIO_CIV5_DAWN_NEWWORLD_TEXT">
      <Text>
DESCRIPTION DU SCÉNARIO[NEWLINE]Nous sommes en 1492. Désireux de traverser l'Atlantique à la recherche d'une route menant jusqu'à la Chine et aux Indes, des explorateurs courtisent les cours d'Angleterre, de France et d'Espagne. Découvriront-ils une route commerciale et la richesse vers les côtes d'Asie ? Ou échoueront-ils sur des terres inconnues ? Les autochtones seront-ils réceptifs et accueillants, ou les repousseront-ils par la force ? Quelles richesses, quelle gloire et quelles opportunités attendent ces navigateurs ? Quel chemin choisirez-vous ? Qui remportera le combat pour la domination du Nouveau Monde ? [NEWLINE][NEWLINE]CONDITIONS DE VICTOIRE[NEWLINE]La victoire revient à la première civilisation qui atteint le score de 1000 points. Vous marquez des points lorsque vous atteignez la Chine en caravelle et lorsque vos unités de la Flotte des Indes rejoignent votre capitale. Jouez autant de fois que vous voulez en essayant les six civilisations : la carte de l'Amérique change à chaque partie. [NEWLINE][NEWLINE]RÈGLES SPÉCIALES[NEWLINE]Toutes les unités navales sont atteintes du scorbut, une "promotion" qui peut leur faire perdre des points de santé dès lors qu'elles terminent un tour en dehors des frontières de l'empire. Construisez l'École de Navigation, une merveille nationale, pour combattre cette maladie. Les puissances européennes ne peuvent pas se déclarer la guerre tant que l'une d'entre elles n'a pas découvert la technologie de la piraterie. Les unités de la Flotte des Indes sont créées lorsque des villes sont rasées ou en découvrant l'Eldorado et la montagne de Potosí, deux merveilles naturelles (si générées sur cette carte). Faites voyager ces unités jusqu'à votre capitale pour gagner de l'or et des points de victoire.</Text>
    </Row>
    <Row Tag="TXT_KEY_NEWWORLD_SCENARIO_CIV5_DAWN_SPAIN_TEXT">
      <Text>
DESCRIPTION DU SCÉNARIO[NEWLINE]Nous sommes en 1492. Désireux de traverser l'Atlantique à la recherche d'une route menant jusqu'à la Chine et aux Indes, des explorateurs courtisent les cours d'Angleterre, de France et d'Espagne. Découvriront-ils une route commerciale et la richesse vers les côtes d'Asie ? Ou échoueront-ils sur des terres inconnues ? Les autochtones seront-ils réceptifs et accueillants, ou les repousseront-ils par la force ? Quelles richesses, quelle gloire et quelles opportunités attendent ces navigateurs ? Quel chemin choisirez-vous ? Qui remportera le combat pour la domination du Nouveau Monde ? [NEWLINE][NEWLINE]CONDITIONS DE VICTOIRE[NEWLINE]La victoire revient à la première civilisation qui atteint le score de 1000 points. Vous marquez des points lorsque vous atteignez la Chine en caravelle et lorsque vos unités de la Flotte des Indes rejoignent votre capitale. Jouez autant de fois que vous voulez en essayant les six civilisations : la carte de l'Amérique change à chaque partie. [NEWLINE][NEWLINE]RÈGLES SPÉCIALES[NEWLINE]Toutes les unités navales sont atteintes du scorbut, une "promotion" qui peut leur faire perdre des points de santé dès lors qu'elles terminent un tour en dehors des frontières de l'empire. Construisez l'École de Navigation, une merveille nationale, pour combattre cette maladie. Les puissances européennes ne peuvent pas se déclarer la guerre tant que l'une d'entre elles n'a pas découvert la technologie de la piraterie. Les unités de la Flotte des Indes sont créées lorsque des villes sont rasées ou en découvrant l'Eldorado et la montagne de Potosí, deux merveilles naturelles (si générées sur cette carte). Faites voyager ces unités jusqu'à votre capitale pour gagner de l'or et des points de victoire.</Text>
    </Row>
    <Row Tag="TXT_KEY_NEWWORLD_SCENARIO_CIV5_HOPI_TEXT">
      <Text>Les Hopis sont l'une des peuplades indigènes du sud-ouest des États-Unis. Ils furent découverts par l'expédition de Coronado en 1540.</Text>
    </Row>
    <Row Tag="TXT_KEY_NEWWORLD_SCENARIO_CIV5_HURON_TEXT">
      <Text>Les Hurons sont l'un des peuples autochtones du Canada. Ils étaient principalement installés sur la côte nord du lac Ontario lors de l'arrivée des premiers européens.</Text>
    </Row>
    <Row Tag="TXT_KEY_NEWWORLD_SCENARIO_CIV5_INUIT_TEXT">
      <Text>Les Inuits sont un peuple autochtone des régions arctiques du Groenland et d'Amérique du Nord.</Text>
    </Row>
    <Row Tag="TXT_KEY_NEWWORLD_SCENARIO_CIV5_LAKOTA_TEXT">
      <Text>Les Lakotas sont une tribu indigène des plaines d'Amérique du Nord.</Text>
    </Row>
    <Row Tag="TXT_KEY_NEWWORLD_SCENARIO_CIV5_MAPUCHE_TEXT">
      <Text>Les Mapuches sont l'une des peuplades indigènes du Chili et de l'Argentine. Les colons espagnols les appelaient les Araucans.</Text>
    </Row>
    <Row Tag="TXT_KEY_NEWWORLD_SCENARIO_CIV5_MAYA_TEXT">
      <Text>Les Mayas sont un peuple autochtone de la péninsule du Yucatan. Leur civilisation se distinguait par ses connaissances en mathématiques et en astronomie, ainsi que par la construction de pyramides en pierres gravées particulièrement complexes.</Text>
    </Row>
    <Row Tag="TXT_KEY_NEWWORLD_SCENARIO_CIV5_MUISCA_TEXT">
      <Text>Les Chibchas sont une peuplade autochtone des montagnes colombiennes. Leur premier contact avec les Espagnols remontent à 1536, et ils sont très probablement à l'origine de la légende de l'Eldorado.</Text>
    </Row>
    <Row Tag="TXT_KEY_NEWWORLD_SCENARIO_CIV5_MUSCOGEE_TEXT">
      <Text>Les Muscogees sont une tribu indigène du sud-est des États-Unis. Ce sont des descendants de la civilisation du Mississippi.</Text>
    </Row>
    <Row Tag="TXT_KEY_NEWWORLD_SCENARIO_CIV5_PRIVATEER_HELP">
      <Text>Unité navale de la Renaissance utilisée pour attaquer les puissances européennes et s'emparer de leurs trésors.</Text>
    </Row>
    <Row Tag="TXT_KEY_NEWWORLD_SCENARIO_CIV5_PRIVATEER_STRATEGY">
      <Text>Le corsaire est l'unité disponible avec la piraterie, une technologie qui doit être découverte pour que les puissances européennes puissent se déclarer la guerre. Utilisez des corsaires pour attaquer des navires ennemis et piller la Flotte des Indes !</Text>
    </Row>
    <Row Tag="TXT_KEY_NEWWORLD_SCENARIO_CIV5_PRIVATEER_TEXT">
      <Text>Voguant sur les flots à la recherche de sa prochaine victime, le corsaire est un pirate "légal", à qui un souverain remet des lettres de marque en lui demandant d'attaquer des navires ennemis en temps de guerre. L'objectif principal du corsaire était d'interrompre les routes commerciales de l'ennemi, affaiblissant ainsi son économie ou sa capacité à équiper une marine marchande et une armée. Le plus souvent, le corsaire était un marchand au flair aiguisé qui possédait déjà son propre navire et un équipage, et connaissait les mers et les routes commerciales. Le corsaire travaillait le plus souvent seul, mais on pouvait parfois croiser des flottes de corsaires, unis pour s'attaquer à des cibles plus importantes.[NEWLINE][NEWLINE]Le corsaire ne cherchait pas à couler le navire ennemi, mais simplement à le capturer et à s'emparer de son chargement. Le butin était en règle générale vendu aux enchères, et l'argent ainsi obtenu était partagé entre le corsaire, son ou ses investisseur(s), et la couronne.
      </Text>
    </Row>
    <Row Tag="TXT_KEY_NEWWORLD_SCENARIO_CIV5_SEMINOLE_TEXT">
      <Text>Les Séminoles sont l'un des peuples indigènes de Floride. Ce sont de proches parents des Muscogees (les deux tribus parlent le creek).</Text>
    </Row>
    <Row Tag="TXT_KEY_NEWWORLD_SCENARIO_CIV5_WABANAKI_TEXT">
      <Text>Les Wabanakis sont le "peuple de l'aube", une tribu indigène des provinces maritimes de l'est du Canada.</Text>
    </Row>
    <Row Tag="TXT_KEY_NEWWORLD_SCENARIO_CIV5_YANOMAMI_TEXT">
      <Text>Les Yanonamis sont une tribu autochtone du bassin amazonien. Leur culture de l'âge de pierre ne fut découverte par les Européens qu'en 1929.</Text>
    </Row>
    <Row Tag="TXT_KEY_NEWWORLD_SCENARIO_CIVILOPEDIA_LEADERS_NAPOLEON_HEADING_1">
      <Text>Histoire</Text>
    </Row>
    <Row Tag="TXT_KEY_NEWWORLD_SCENARIO_CIVILOPEDIA_LEADERS_NAPOLEON_LIVED">
      <Text>1494 - 1547</Text>
    </Row>
    <Row Tag="TXT_KEY_NEWWORLD_SCENARIO_CIVILOPEDIA_LEADERS_NAPOLEON_SUBTITLE">
      <Text>Roi de France</Text>
    </Row>
    <Row Tag="TXT_KEY_NEWWORLD_SCENARIO_CIVILOPEDIA_LEADERS_NAPOLEON_TEXT_1">
      <Text>François 1er régna sur la France de 1515 à 1547, période au cours de laquelle il fonda une alliance franco-ottomane avec le sultan Soliman le Magnifique. Son principal rival était l'empereur du Saint Empire romain germanique Charles Quint, contre lequel le roi lança plusieurs campagnes militaires. François 1er fut fait prisonnier à l'issue de la bataille de Pavie en 1525. Il fut détenu pendant plus d'un an et dut livrer ses deux fils, Henri et François, pour recouvrer sa liberté.</Text>
    </Row>
    <Row Tag="TXT_KEY_NEWWORLD_SCENARIO_CONQUISTADOR_BALBOA">
      <Text>Balboa</Text>
    </Row>
    <Row Tag="TXT_KEY_NEWWORLD_SCENARIO_CONQUISTADOR_CORDOVA">
      <Text>Córdova</Text>
    </Row>
    <Row Tag="TXT_KEY_NEWWORLD_SCENARIO_CONQUISTADOR_CORONADO">
      <Text>Coronado</Text>
    </Row>
    <Row Tag="TXT_KEY_NEWWORLD_SCENARIO_CONQUISTADOR_CORTES">
      <Text>Cortés</Text>
    </Row>
    <Row Tag="TXT_KEY_NEWWORLD_SCENARIO_CONQUISTADOR_DEVEREUX">
      <Text>Dévereux</Text>
    </Row>
    <Row Tag="TXT_KEY_NEWWORLD_SCENARIO_CONQUISTADOR_LAUDONNIERRE">
      <Text>Laudonnière</Text>
    </Row>
    <Row Tag="TXT_KEY_NEWWORLD_SCENARIO_CONQUISTADOR_MONTEJO">
      <Text>Montejo</Text>
    </Row>
    <Row Tag="TXT_KEY_NEWWORLD_SCENARIO_CONQUISTADOR_MOUNTJOY">
      <Text>Mountjoy</Text>
    </Row>
    <Row Tag="TXT_KEY_NEWWORLD_SCENARIO_CONQUISTADOR_NORREYS">
      <Text>Norreys</Text>
    </Row>
    <Row Tag="TXT_KEY_NEWWORLD_SCENARIO_CONQUISTADOR_ORELLANA">
      <Text>Orellana</Text>
    </Row>
    <Row Tag="TXT_KEY_NEWWORLD_SCENARIO_CONQUISTADOR_PIZARRO">
      <Text>Pizarro</Text>
    </Row>
    <Row Tag="TXT_KEY_NEWWORLD_SCENARIO_CONQUISTADOR_RIBAULT">
      <Text>Ribault</Text>
    </Row>
    <Row Tag="TXT_KEY_NEWWORLD_SCENARIO_CONQUISTADOR_SMITH">
      <Text>Smith</Text>
    </Row>
    <Row Tag="TXT_KEY_NEWWORLD_SCENARIO_CONQUISTADOR_VILLEGAGNON">
      <Text>Villegagnon</Text>
    </Row>
    <Row Tag="TXT_KEY_NEWWORLD_SCENARIO_CONQUISTADOR_WINTHROP">
      <Text>Winthrop</Text>
    </Row>
    <Row Tag="TXT_KEY_NEWWORLD_SCENARIO_DESC">
      <Text>Naviguez vers l'ouest à la recherche d'un passage vers l'orient, et faites des découvertes. Ou incarnez une civilisation amérindienne et faites face à une étrange menace venue de la mer.</Text>
    </Row>
    <Row Tag="TXT_KEY_NEWWORLD_SCENARIO_DIPLO_MAY_NOT_ATTACK_MOD">
      <Text>Ne peut attaquer ce joueur jusqu'à ce que vous découvrez la technologie Piraterie.</Text>
    </Row>
    <Row Tag="TXT_KEY_NEWWORLD_SCENARIO_DIPLO_MY_SCORE_FUTURE_TECH">
      <Text>{1_Num} pour les trésors</Text>
    </Row>
    <Row Tag="TXT_KEY_NEWWORLD_SCENARIO_DIPLO_MY_SCORE_WONDERS">
      <Text>{1_Num} pour les merveilles de Chine</Text>
    </Row>
    <Row Tag="TXT_KEY_NEWWORLD_SCENARIO_DIPLO_RESCH_AGREEMENT_NO_TECH">
      <Text>Vous ne pouvez pas échanger d'Accords de Recherche dans ce scénario.</Text>
    </Row>
    <Row Tag="TXT_KEY_NEWWORLD_SCENARIO_FIRST_CIRCUMNAVIGATION">
      <Text>{@1: gender m?Un ; f?Une ;}{@1_UnitName} a atteint la Chine ! Pour cette première circumnavigation, vous recevez {2_GoldAmount} [ICON_GOLD] Or et {3_VPAmount} points de victoire. Deux autres caravelles peuvent encore être récompensées pour avoir navigué jusqu'en Chine.</Text>
    </Row>
    <Row Tag="TXT_KEY_NEWWORLD_SCENARIO_FIRST_ENGLISH_EXPLORER">
      <Text>Cabot</Text>
    </Row>
    <Row Tag="TXT_KEY_NEWWORLD_SCENARIO_FIRST_FRENCH_EXPLORER">
      <Text>Verrazzano</Text>
    </Row>
    <Row Tag="TXT_KEY_NEWWORLD_SCENARIO_FIRST_SPANISH_EXPLORER">
      <Text>Colomb</Text>
    </Row>
    <Row Tag="TXT_KEY_NEWWORLD_SCENARIO_LEADER_NAPOLEON_FIRSTGREETING_1">
      <Text>Bienvenue. Je suis François Ier, grand protecteur des arts de la Renaissance !</Text>
    </Row>
    <Row Tag="TXT_KEY_NEWWORLD_SCENARIO_LEADER_NAPOLEON_FIRSTGREETING_2">
      <Text>Je vous souhaite la bienvenue ! Je suis François Ier, roi de France. Je suis fidèle à mes amis, et impitoyable envers mes ennemis. Quel camp allez-vous choisir ?</Text>
    </Row>
    <Row Tag="TXT_KEY_NEWWORLD_SCENARIO_LEADER_NAPOLEON_FIRSTGREETING_3">
      <Text>Ah. Vous voilà enfin. Je suis François Ier, roi de France. Nous devons convenir d'une répartition des territoires du Nouveau Monde entre nos deux grandes nations.</Text>
    </Row>
    <Row Tag="TXT_KEY_NEWWORLD_SCENARIO_LEADER_NAPOLEON_FIRSTGREETING_4">
      <Text>Salutations. Je suis François Ier, roi de France. Vous voulez voir le dernier de mes châteaux ?</Text>
    </Row>
    <Row Tag="TXT_KEY_NEWWORLD_SCENARIO_MISC_YOU_UNIT_WAS_DAMAGED_ATTRITION">
      <Text>Scorbut</Text>
    </Row>
    <Row Tag="TXT_KEY_NEWWORLD_SCENARIO_MISC_YOU_UNIT_WAS_DESTROYED_ATTRITION">
      <Text>Le scorbut a provoqué la mort de votre {@1_UnitName} !</Text>
    </Row>
    <Row Tag="TXT_KEY_NEWWORLD_SCENARIO_OTHER_CIRCUMNAVIGATION">
      <Text>Un explorateur de {@1_PlyrName} a atteint la Chine. Encore {2_Num} autre(s) caravelle(s) peuvent recevoir de l'or et des points de victoire pour avoir navigué jusqu'en Chine.</Text>
    </Row>
    <Row Tag="TXT_KEY_NEWWORLD_SCENARIO_PRIVATEER_CAVENDISH">
      <Text>Cavendish</Text>
    </Row>
    <Row Tag="TXT_KEY_NEWWORLD_SCENARIO_PRIVATEER_DE_SORES">
      <Text>De Sores</Text>
    </Row>
    <Row Tag="TXT_KEY_NEWWORLD_SCENARIO_PRIVATEER_DRAKE">
      <Text>Drake</Text>
    </Row>
    <Row Tag="TXT_KEY_NEWWORLD_SCENARIO_PRIVATEER_FLEURY">
      <Text>Fleury</Text>
    </Row>
    <Row Tag="TXT_KEY_NEWWORLD_SCENARIO_PRIVATEER_FROBISHER">
      <Text>Frobisher</Text>
    </Row>
    <Row Tag="TXT_KEY_NEWWORLD_SCENARIO_PRIVATEER_GILBERT">
      <Text>Gilbert</Text>
    </Row>
    <Row Tag="TXT_KEY_NEWWORLD_SCENARIO_PRIVATEER_HAWKINS">
      <Text>Hawkins</Text>
    </Row>
    <Row Tag="TXT_KEY_NEWWORLD_SCENARIO_PRIVATEER_LE_CLERC">
      <Text>Le Clerc</Text>
    </Row>
    <Row Tag="TXT_KEY_NEWWORLD_SCENARIO_PRIVATEER_LE_TESTU">
      <Text>Le Testu</Text>
    </Row>
    <Row Tag="TXT_KEY_NEWWORLD_SCENARIO_PRIVATEER_MENENDEZ">
      <Text>Menéndez</Text>
    </Row>
    <Row Tag="TXT_KEY_NEWWORLD_SCENARIO_PRIVATEER_RALEIGH">
      <Text>Raleigh</Text>
    </Row>
    <Row Tag="TXT_KEY_NEWWORLD_SCENARIO_PRIVATEER_SANTA_CRUZ">
      <Text>Santa Cruz</Text>
    </Row>
    <Row Tag="TXT_KEY_NEWWORLD_SCENARIO_SECOND_CIRCUMNAVIGATION">
      <Text>{@1: gender m?Un ; f?Une ;}{@1_UnitName} a atteint la Chine ! Pour cette deuxième circumnavigation, vous recevez {2_GoldAmount} [ICON_GOLD] Or et {3_VPAmount} points de victoire. Une autre caravelle peut encore être récompensée pour avoir navigué jusqu'en Chine.</Text>
    </Row>
    <Row Tag="TXT_KEY_NEWWORLD_SCENARIO_TECH_EDUCATION_HELP">
      <Text>Permet la construction du [COLOR_POSITIVE_TEXT]tribunal[ENDCOLOR], un bâtiment qui diminue le [ICON_HAPPINESS_4] mécontentement généré par les villes [ICON_OCCUPIED] occupées. Offre également divers autres bénéfices à la [ICON_RESEARCH] science.</Text>
    </Row>
    <Row Tag="TXT_KEY_NEWWORLD_SCENARIO_TECH_IMPERIALISM_DESC">
      <Text>Dans sa forme la plus simple, l'impérialisme décrit une relation inéquitable entre deux nations, où l'une exerce un certain contrôle sur l'autre, le plus souvent au sein d'un empire. On trouve la trace de dynasties impérialistes partout dans le monde, depuis la Chine jusqu'à Rome, en passant par la Grande-Bretagne, et le concept même d'impérialisme existe depuis des milliers d'années ; on peut pour ainsi dire considérer qu'il a vu le jour avec celui de gouvernement. Ce n'est cependant qu'au XVIe siècle que le terme fait son apparition pour décrire la politique étrangère de nations comme l'Espagne, la Grande-Bretagne, la Belgique et les Pays-Bas, très occupées à nouer des liens impériaux avec les Amériques. [NEWLINE][NEWLINE]Bien que l'impérialisme soit traditionnellement le fait de grands empires militaires, il peut aussi se présenter de façon plus discrète. Il n'est pas obligatoire d'exercer un contrôle officiel sur le gouvernement du pays le plus faible, et une civilisation puissante pourra parfois en dominer une plus faible uniquement par des voies indirectes (économiques, politiques ou même religieuses).
      </Text>
    </Row>
    <Row Tag="TXT_KEY_NEWWORLD_SCENARIO_TECH_IMPERIALISM_HELP">
      <Text>Permet la production du [COLOR_POSITIVE_TEXT]conquistador[ENDCOLOR], une unité spécialisée dans l'exploration et la colonisation par-delà les mers.</Text>
    </Row>
    <Row Tag="TXT_KEY_NEWWORLD_SCENARIO_TECH_IMPERIALISM_QUOTE">
      <Text>[NEWLINE][TAB][TAB]"L'impérialisme est un tigre de papier."[NEWLINE][TAB][TAB] - Mao Tsé-Tung[NEWLINE][TAB]</Text>
    </Row>
    <Row Tag="TXT_KEY_NEWWORLD_SCENARIO_TECH_MATHEMATICS_HELP">
      <Text>Permet la construction de la [COLOR_POSITIVE_TEXT]catapulte[ENDCOLOR], une puissante arme de siège.</Text>
    </Row>
    <Row Tag="TXT_KEY_NEWWORLD_SCENARIO_TECH_NAVAL_TRADITION_DESC">
      <Text>La tradition navale décrit aussi bien l'empressement d'une civilisation à explorer les mers et sa marine militaire, que les us et coutumes navals de cette marine. De nombreuses civilisations insulaires ou côtières, comme la Grande-Bretagne et l'Espagne, disposent d'une tradition navale séculaire, l'océan ayant joué un rôle essentiel dans leur développement économique et politique. Tandis que certains pays enclavés utilisaient des soldats de métier pour préserver la paix et faire la guerre, les nations maritimes leur préféraient flottes et flottilles, qu'elles entretenaient afin d'arpenter les mers à la recherche de navires ennemis et pirates. [NEWLINE][NEWLINE]De nombreuses traditions ayant vu le jour au sein des premières marines de ces pays ont toujours cours chez les marins d'aujourd'hui, tandis que d'autres ont dépassé le pont de leurs bateaux pour se propager auprès de la population terrestre. Certaines habitudes, comme le port de pantalons à pattes d'éléphant ou de boutons de manchette, nous viennent tout droit de ces traditions navales !
      </Text>
    </Row>
    <Row Tag="TXT_KEY_NEWWORLD_SCENARIO_TECH_NAVAL_TRADITION_HELP">
      <Text>L'éveil du Nouveau Monde</Text>
    </Row>
    <Row Tag="TXT_KEY_NEWWORLD_SCENARIO_TECH_NAVAL_TRADITION_QUOTE">
      <Text>[NEWLINE][TAB][TAB]"Ne me parlez pas de tradition navale ! Ce n'est que rhum, sodomie et coups de fouet."[NEWLINE][TAB][TAB] - Winston Churchill[NEWLINE][TAB]</Text>
    </Row>
    <Row Tag="TXT_KEY_NEWWORLD_SCENARIO_TECH_NAVIGATION_HELP">
      <Text>Permet la construction de l'[COLOR_POSITIVE_TEXT]École de Navigation[ENDCOLOR], un bâtiment qui éradique le scorbut chez vos unités navales. Permet également aux villes côtières de construire un [COLOR_POSITIVE_TEXT]chantier naval[ENDCOLOR], grâce auquel les ressources maritimes génèrent de la [ICON_PRODUCTION] production.</Text>
    </Row>
    <Row Tag="TXT_KEY_NEWWORLD_SCENARIO_TECH_PIRACY_DESC">
      <Text>Les raids, les pillages, les violences en mer... Ah, la vie de pirate est un vrai délice ! Bien que souvent représentés de façon romanesque au cinéma et dans les médias, les pirates n'ont cependant rien de l'esprit et de l'humour dont peuvent faire preuve le capitaine Jack Sparrow et consorts dans les films que l'on connaît. Ces criminels des mers volaient les marchandises des autres navires par la force, pillaient les villes côtières, et n'étaient rien de plus qu'une menace constante pour les sociétés civilisées. La piraterie a très probablement vu le jour en même temps que le transport maritime ; l'un des premiers incidents rapportés remonte au XIIIe av. J.-C. ! [NEWLINE][NEWLINE]On attribue certains des actes de piraterie les plus célèbres aux Vikings, qui terrorisaient les côtes européennes, et aux pirates des Caraïbes, qui prenaient un malin plaisir à s'approprier les richesses transportées par la Flotte des Indes espagnole. Cette époque "bénie" pour les pirates est celle que l'on retrouve le plus souvent dans les films et les livres ; elle s'étend de 1560 à 1720. Bien que ce brave flibustier armé d'un sabre et surmonté d'un joli chapeau n'écume plus aujourd'hui que les œuvres de fiction, on peut toujours croiser des pirates sur la plupart des mers du monde, et plus particulièrement près des côtes de la péninsule arabe. Attention cependant à ne pas confondre pirates et corsaires, ces derniers exerçant une sorte de raid naval, avec l'autorisation des gouvernements, le plus souvent en temps de guerre.
      </Text>
    </Row>
    <Row Tag="TXT_KEY_NEWWORLD_SCENARIO_TECH_PIRACY_HELP">
      <Text>Permet la production du [COLOR_POSITIVE_TEXT]corsaire[ENDCOLOR] et autorise les puissances européennes à se déclarer la guerre.</Text>
    </Row>
    <Row Tag="TXT_KEY_NEWWORLD_SCENARIO_TECH_PIRACY_QUOTE">
      <Text>[NEWLINE][TAB][TAB]"Il n'y a que deux règles qui comptent, ici : ce qu'un homme peut faire, et ce qu'il ne peut pas faire. Je peux te laisser couler, mais je pourrai pas ramener ce bateau tout seul à Tortuga, tu vois ? Alors, soit tu peux naviguer sous les ordres d'un pirate, soit tu ne peux pas."[NEWLINE][TAB][TAB] - Capitaine Jack Sparrow[NEWLINE][TAB]</Text>
    </Row>
    <Row Tag="TXT_KEY_NEWWORLD_SCENARIO_TECH_PROSOLDIERS_DESC">
      <Text>Les soldats de métier sont une avancée majeure sur les milices composées de petites frappes et rassemblées à la va-vite que l'on retrouve dans la plupart des civilisations primitives. Ces soldats à plein temps sont mieux équipés, mieux entraînés, et de façon générale plus efficace qu'un paysan vêtu d'un pourpoint en cuir brandissant une fourche d'un air revêche. L'Empire romain est à l'origine de l'une des toutes premières armées de métier au monde, sans laquelle il n'aurait peut-être pas accumulé les victoires aussi facilement. En Europe, les premiers soldats de métier furent embauchés par Charles VII de France en 1445, puis par le roi Jacques II d'Angleterre en 1685. [NEWLINE][NEWLINE]L'armée de métier forme la base des systèmes de défense modernes, et on la retrouve dans la majorité des pays développés.
      </Text>
    </Row>
    <Row Tag="TXT_KEY_NEWWORLD_SCENARIO_TECH_PROSOLDIERS_HELP">
      <Text>Permet la production du [COLOR_POSITIVE_TEXT]Tercio[ENDCOLOR], une unité de combat rapproché dominante.</Text>
    </Row>
    <Row Tag="TXT_KEY_NEWWORLD_SCENARIO_TECH_PROSOLDIERS_QUOTE">
      <Text>[NEWLINE][TAB][TAB]"Bien que soldat de profession, je n'ai jamais particulièrement apprécié la guerre, et je ne l'ai jamais recommandée, si ce n'est pour rétablir la paix."[NEWLINE][TAB][TAB] - Ulysses S. Grant[NEWLINE][TAB]</Text>
    </Row>
    <Row Tag="TXT_KEY_NEWWORLD_SCENARIO_TECH_RELIGIOUS_ORDERS_DESC">
      <Text>On retrouve dans la plupart des religions du monde des communautés et des organisations spéciales regroupant des individus particulièrement pieux et désireux de vivre en marge de la société, le plus souvent pour être en accord avec les préceptes de leur foi. Ces congrégations monastiques sont en règle générale abritées dans des monastères, des bâtiments où les dévots peuvent vivre et travailler en paix. [NEWLINE][NEWLINE]Si certaines congrégations se satisfont de pouvoir vivre et prier dans leur pays d'origine, d'autres n'ont vu le jour que dans le but de faire découvrir leur croyance à d'autres peuples. Ainsi, les missionnaires jésuites des Amériques traversèrent l'Atlantique pour installer des monastères et des missions sur le sol américain, où ils enseignèrent aux autochtones les bases de leur foi et de l'éducation occidentale.
      </Text>
    </Row>
    <Row Tag="TXT_KEY_NEWWORLD_SCENARIO_TECH_RELIGIOUS_ORDERS_HELP">
      <Text>Permet la construction du [COLOR_POSITIVE_TEXT]monastère[ENDCOLOR], un bâtiment qui accélère l'expansion des frontières culturelles d'une ville.</Text>
    </Row>
    <Row Tag="TXT_KEY_NEWWORLD_SCENARIO_TECH_RELIGIOUS_ORDERS_QUOTE">
      <Text>[NEWLINE][TAB][TAB]"Les Jésuites qui sont morts et ont passé leur vie à enseigner sont bien les gens dont on se souvient le moins."[NEWLINE][TAB][TAB] - Daniel Berrigan[NEWLINE][TAB]</Text>
    </Row>
    <Row Tag="TXT_KEY_NEWWORLD_SCENARIO_TECH_ROYAL_GUARDS_DESC">
      <Text>Le plus souvent composée d'un groupe d'élite de serviteurs armés, la garde royale est l'unité militaire ou de cérémonie traditionnelle utilisée pour protéger la famille royale ou les membres les plus éminents du clergé. Historiquement, ces membres d'élite jouaient aussi un double rôle politique ; en effet, leur position unique leur permettait tantôt d'influer sur l'opinion d'un monarque tantôt de jouer un rôle essentiel lors des révoltes ou des coups d'État. [NEWLINE][NEWLINE]Certains régiments de gardes royaux ont aussi trouvé la gloire en dehors des frontières de leur pays, comme les "Tropas de la Casa Real" espagnoles ou les Mousquetaires français. Les Mousquetaires n'étaient techniquement qu'une sous-unité de la garde royale française, dépendant des gardes du corps du roi, eux-mêmes chargés d'assurer la plupart des protections. Mais grâce notamment à l'œuvre d'Alexandre Dumas, "Les Trois Mousquetaires", ils sont aujourd'hui parmi les gardes royaux les plus populaires et reconnus, toutes civilisations confondues.
      </Text>
    </Row>
    <Row Tag="TXT_KEY_NEWWORLD_SCENARIO_TECH_ROYAL_GUARDS_HELP">
      <Text>Permet la production du [COLOR_POSITIVE_TEXT]mousquetaire[ENDCOLOR], une version améliorée de l'arquebusier traditionnel.</Text>
    </Row>
    <Row Tag="TXT_KEY_NEWWORLD_SCENARIO_TECH_ROYAL_GUARDS_QUOTE">
      <Text>[NEWLINE][TAB][TAB]"Ce monde est incertain et rempli de dangers. L'honneur est sapé par la soif de pouvoir, la liberté sacrifiée lorsque les faibles sont opprimés par les puissants. Mais il y a ceux qui s'opposent à ces forces, qui consacrent leur vie à la vérité, l'honneur et la liberté. On appelle ces hommes des Mousquetaires."[NEWLINE][TAB][TAB] - Louis XIII[NEWLINE][TAB]</Text>
    </Row>
    <Row Tag="TXT_KEY_NEWWORLD_SCENARIO_TECH_TRAPPING_HELP">
      <Text>Permet à vos ouvriers de construire des [COLOR_POSITIVE_TEXT]campements[ENDCOLOR] sur les sources de [ICON_RES_DEER] cervidés, d'[ICON_RES_IVORY] ivoire et de [ICON_RES_FUR] fourrure[ENDCOLOR], qui augmentent la production d'[ICON_GOLD] or des cases concernées.</Text>
    </Row>
    <Row Tag="TXT_KEY_NEWWORLD_SCENARIO_TECH_TREASURE_FLEET_DESC">
      <Text>Une fois les Espagnols bien implantés aux Amériques et prêts à renvoyer leurs découvertes et leurs trésors en Europe, il leur fallut développer un nouveau système de navigation, plus efficace, afin d'éviter les attaques des pirates. C'est ainsi que naquit la Flotte des Indes, un convoi spécial soumis à des règles strictes aussi bien lors de son séjour à quai qu'une fois en mer. Les navires en partance des Amériques devaient voyager en masse le long d'un couloir maritime précis, ce qui facilitait leur protection par une force armée de taille relativement réduite. Ces navires ne rejoignaient par la suite que certaines villes portuaires spécifiques (comme Séville), ce qui diminuait une fois encore les risques d'attaques pirates. [NEWLINE][NEWLINE]La Flotte des Indes fut utilisée avec beaucoup de succès par l'Espagne entre le XVIe et le XVIIIe siècles, et reste à ce jour l'une des opérations navales les plus rentables et efficaces de toute l'histoire. Malheureusement, la perte de certaines villes le long des côtes de l'Empire espagnol au cours du XVIIe siècle commença à menacer la survie de la flotte. Cherchant à combattre ce problème, le roi Charles III assouplit les lois du système en 1765, et donna accès à la flotte à de plus en plus de colonies au cours des années 1780. La dernière flotte complète effectua la traversée en 1790, et les voyages entre les deux continents furent ensuite laissés aux soins de plus petits groupes de navires, en fonction des besoins du moment.
      </Text>
    </Row>
    <Row Tag="TXT_KEY_NEWWORLD_SCENARIO_TECH_TREASURE_FLEET_HELP">
      <Text>Offre la promotion [COLOR_POSITIVE_TEXT]Embarcation défensive[ENDCOLOR] à toutes les unités terrestres, ce qui leur permet de se défendre contre les attaques navales.</Text>
    </Row>
    <Row Tag="TXT_KEY_NEWWORLD_SCENARIO_TECH_TREASURE_FLEET_QUOTE">
      <Text>[NEWLINE][TAB][TAB]"L'or est un trésor, et celui qui le possède peut tout accomplir dans ce monde et aider les âmes à rejoindre le paradis."[NEWLINE][TAB][TAB] - Christophe Colomb[NEWLINE][TAB]</Text>
    </Row>
    <Row Tag="TXT_KEY_NEWWORLD_SCENARIO_TECH_WARSHIPS_DESC">
      <Text>Bien que de nombreux bateaux soient conçus pour traverser les océans rapidement ou pour embarquer la plus grosse cargaison possible, les navires de guerre n'ont toujours eu qu'une seule fonction : détruire d'autres navires. En plus d'être, comme de bien entendu, équipés de certaines armes (le plus souvent, des canons ou des béliers), les navires de guerre sont en mesure de supporter plus de dégâts que leurs homologues traditionnels, et sont aussi bien plus maniables. [NEWLINE][NEWLINE]Les navires de guerre se sont développés en parallèle des technologies navales. Les premiers d'entre eux prirent la forme de galères et de trirèmes, capables d'éperonner les embarcations ennemies, mais les combats étaient le plus souvent l'œuvre des soldats à leur bord. Cependant, une fois qu'il devint possible de recharger rapidement les obus, on utilisa de grands voiliers équipés de rangées de canons de chaque côté du bateau. On finit naturellement par abandonner ces navires en bois pour d'autres, faits de fer et d'acier, et les voiles firent place à la vapeur et au nucléaire. Bien que les navires de guerre modernes n'aient plus grand-chose en commun avec les galères d'antan, ils conservent la même fonctionnalité élémentaire : être capables de couler l'autre bateau avant qu'il ne vous coule.
      </Text>
    </Row>
    <Row Tag="TXT_KEY_NEWWORLD_SCENARIO_TECH_WARSHIPS_HELP">
      <Text>Permet la construction de la [COLOR_POSITIVE_TEXT]frégate[ENDCOLOR], l'unité navale la plus puissante de la Renaissance.</Text>
    </Row>
    <Row Tag="TXT_KEY_NEWWORLD_SCENARIO_TECH_WARSHIPS_QUOTE">
      <Text>[NEWLINE][TAB][TAB]"Au diable les torpilles, en avant toute !"[NEWLINE][TAB][TAB] - Amiral David Glasgow Farragut[NEWLINE][TAB]</Text>
    </Row>
    <Row Tag="TXT_KEY_NEWWORLD_SCENARIO_THIRD_CIRCUMNAVIGATION">
      <Text>{@1: gender m?Un ; f?Une ;}{@1_UnitName} a atteint la Chine ! Pour cette troisième circumnavigation, vous recevez {2_GoldAmount} [ICON_GOLD] Or et {3_VPAmount} points de victoire. Naviguer jusqu'en Chine ne rapportera plus de récompenses.</Text>
    </Row>
    <Row Tag="TXT_KEY_NEWWORLD_SCENARIO_TITLE">
      <Text>Conquête du Nouveau Monde</Text>
    </Row>
    <Row Tag="TXT_KEY_NEWWORLD_SCENARIO_TRAIT_CITY_STATE_FRIENDSHIP_SHORT">
      <Text>Alliés indigènes</Text>
    </Row>
    <Row Tag="TXT_KEY_NEWWORLD_SCENARIO_TREASURE_CAPTURED_CITY">
      <Text>La capture de {@1_CityName} a généré 3 trésors.	
	
</Text>
    </Row>
    <Row Tag="TXT_KEY_NEWWORLD_SCENARIO_TREASURE_FOUND">
      <Text>Trésor(s) trouvé(s)</Text>
    </Row>
    <Row Tag="TXT_KEY_NEWWORLD_SCENARIO_TREASURE_NATURAL_WONDER">
      <Text>Un trésor a été découvert près {@1: plural 1?{@1: gender *:vowel?de l'; m?du ; f?de la ;}; 2?des ;}{@1_NWName}.</Text>
    </Row>
    <Row Tag="TXT_KEY_NEWWORLD_SCENARIO_TREASURE_RAZED_CITY">
      <Text>En rasant {@1_CityName}, un trésor a vu le jour.</Text>
    </Row>
    <Row Tag="TXT_KEY_NEWWORLD_SCENARIO_TREASURE_RETURNED">
      <Text>Un trésor a été rapporté à {@1_CityName}, vous rapportant {2_GoldAmount} [ICON_GOLD] Or et {3_VPAmount} points de victoire.</Text>
    </Row>
    <Row Tag="TXT_KEY_NEWWORLD_SCENARIO_TREASURE_RETURNED_SHORT">
      <Text>Trésor(s) rapporté(s)</Text>
    </Row>
    <Row Tag="TXT_KEY_NEWWORLD_SCENARIO_TURNSREMAINING">
      <Text>Tours restants : {1_TurnsRemaining}</Text>
    </Row>
    <Row Tag="TXT_KEY_NEWWORLD_SCENARIO_UNIT_PRIVATEER">
      <Text>Corsaire</Text>
    </Row>
    <Row Tag="TXT_KEY_NEWWORLD_SCENARIO_UNIT_TREASURE_STRATEGY">
      <Text>Unité civile exclusive à ce scénario qui représente une caravane de mulets sur terre, ou de navires de la Flotte des Indes sur mer. Elle transporte de l'or ou de l'argent trouvé au Nouveau Monde. Faites-lui rejoindre votre capitale pour gagner de l'or et des points de victoire.</Text>
    </Row>
    <Row Tag="TXT_KEY_NEWWORLD_SCENARIO_UNITS_TREASURE_TEXT">
      <Text>La Flotte des Indes est le nom donné au système de flotte espagnol dans le Nouveau Monde, depuis les mines jusqu'à la destination finale. Une fois l'or ou l'argent excavé à divers endroits des Amériques, il était transporté à dos de lamas ou de mulets jusqu'à des ports bien précis le long de la côte de l'empire. Depuis ces ports, le trésor était ensuite chargé sur des galions et des navires marchands, qui traversaient ensemble l'Atlantique, formant un impressionnant convoi. Ces navires rejoignaient l'Espagne via une route très précise, ce qui leur permettait d'être facilement protégés contre les pirates et les bandits. En plus d'avoir permis à l'Espagne de devenir la civilisation la plus prospère de l'époque, cette flotte a également joué un rôle majeur dans la mise en place de l'un des systèmes navals les plus impressionnants au monde.</Text>
    </Row>
    <Row Tag="TXT_KEY_NEWWORLD_SCENARIO_VP_FUTURE_TECH">
      <Text>Trésors</Text>
    </Row>
    <Row Tag="TXT_KEY_NEWWORLD_SCENARIO_VP_WONDERS">
      <Text>Merveilles/Chine</Text>
    </Row>
    <Row Tag="TXT_KEY_PEDIA_PROMOTION_SCURVY">
      <Text>Scorbut</Text>
    </Row>
    <Row Tag="TXT_KEY_PROMOTION_SCURVY">
      <Text>Scorbut</Text>
    </Row>
    <Row Tag="TXT_KEY_PROMOTION_SCURVY_HELP">
      <Text>65% de chances de perdre un point de vie si l'unité termine le tour en territoire hostile ou inconnu.</Text>
    </Row>
  </Language_FR_FR>
</GameData>