<?xml version="1.0" encoding="utf-8"?>
<!--Generated with LocalizationBuddy.-->
<!--Copyright Firaxis Games 2010-->
<!--All Rights Reserved-->
<GameData>
  <Language_IT_IT>
    <Row Tag="TXT_KEY_POLYNESIAN_SCENARIO_CIV_AZTEC_ADJECTIVE">
      <Text>tongano|tongana|tongani|tongane</Text>
      <Gender>masculine|feminine|masculine|feminine</Gender>
      <Plurality>1|1|2|2</Plurality>
    </Row>
    <Row Tag="TXT_KEY_POLYNESIAN_SCENARIO_CIV_AZTEC_DESC">
      <Text>Impero di Tonga</Text>
      <Gender>masculine</Gender>
      <Plurality>1</Plurality>
    </Row>
    <Row Tag="TXT_KEY_POLYNESIAN_SCENARIO_CIV_AZTEC_SHORT_DESC">
      <Text>Tonga|di Tonga|a Tonga|Tonga|da Tonga</Text>
      <Gender>feminine</Gender>
      <Plurality>1</Plurality>
    </Row>
    <Row Tag="TXT_KEY_POLYNESIAN_SCENARIO_CIV_INDIA_ADJECTIVE">
      <Text>samoano|samoana|samoani|samoane</Text>
      <Gender>masculine|feminine|masculine|feminine</Gender>
      <Plurality>1|1|2|2</Plurality>
    </Row>
    <Row Tag="TXT_KEY_POLYNESIAN_SCENARIO_CIV_INDIA_DESC">
      <Text>Impero Samoa</Text>
      <Gender>masculine</Gender>
      <Plurality>1</Plurality>
    </Row>
    <Row Tag="TXT_KEY_POLYNESIAN_SCENARIO_CIV_INDIA_SHORT_DESC">
      <Text>Samoa|di Samoa|a Samoa|Samoa|da Samoa</Text>
      <Gender>feminine</Gender>
      <Plurality>1</Plurality>
    </Row>
    <Row Tag="TXT_KEY_POLYNESIAN_SCENARIO_CIV_IROQUOIS_ADJECTIVE">
      <Text>tahitiano|tahitiana|tahitiani|tahitiane</Text>
      <Gender>masculine|feminine|masculine|feminine</Gender>
      <Plurality>1|1|2|2</Plurality>
    </Row>
    <Row Tag="TXT_KEY_POLYNESIAN_SCENARIO_CIV_IROQUOIS_DESC">
      <Text>Impero di Tahiti</Text>
      <Gender>masculine</Gender>
      <Plurality>1</Plurality>
    </Row>
    <Row Tag="TXT_KEY_POLYNESIAN_SCENARIO_CIV_IROQUOIS_SHORT_DESC">
      <Text>Tahiti|di Tahiti|a Tahiti|Tahiti|da Tahiti</Text>
      <Gender>feminine</Gender>
      <Plurality>1</Plurality>
    </Row>
    <Row Tag="TXT_KEY_POLYNESIAN_SCENARIO_CIV_POLYNESIA_ADJECTIVE">
      <Text>di Hiva</Text>
    </Row>
    <Row Tag="TXT_KEY_POLYNESIAN_SCENARIO_CIV_POLYNESIA_DESC">
      <Text>Impero di Hiva</Text>
      <Gender>masculine</Gender>
      <Plurality>1</Plurality>
    </Row>
    <Row Tag="TXT_KEY_POLYNESIAN_SCENARIO_CIV_POLYNESIA_SHORT_DESC">
      <Text>Hiva|di Hiva|a Hiva|Hiva|da Hiva</Text>
      <Gender>feminine</Gender>
      <Plurality>1</Plurality>
    </Row>
  </Language_IT_IT>
</GameData>