<?xml version="1.0" encoding="utf-8"?>
<!--Generated with LocalizationBuddy.-->
<!--Copyright Firaxis Games 2010-->
<!--All Rights Reserved-->
<GameData>
  <Language_PL_PL>
    <Row Tag="TXT_KEY_LEADER_KAMEHAMEHA_AGREE_SHORT_1">
      <Text>Dobrze.</Text>
    </Row>
    <Row Tag="TXT_KEY_LEADER_KAMEHAMEHA_AGREE_SHORT_2">
      <Text>Niech będzie.</Text>
    </Row>
    <Row Tag="TXT_KEY_LEADER_KAMEHAMEHA_AGREE_SHORT_3">
      <Text>Oczywiście.</Text>
    </Row>
    <Row Tag="TXT_KEY_LEADER_KAMEHAMEHA_AGREE_SHORT_4">
      <Text>Ech, w porządku.</Text>
    </Row>
    <Row Tag="TXT_KEY_LEADER_KAMEHAMEHA_ATTACKED_1">
      <Text>Ośmielasz się ignorować prawa strzaskanego wiosła? Nasz konflikt wielce mnie smuci, ale muszę chronić swój lud.</Text>
    </Row>
    <Row Tag="TXT_KEY_LEADER_KAMEHAMEHA_ATTACKED_2">
      <Text>Widzę teraz, że głupio było wierzyć w twe dobre intencje przy podziałach łupów i bogactw. Powstrzymam cię, nim uda ci się oszukać innych.</Text>
    </Row>
    <Row Tag="TXT_KEY_LEADER_KAMEHAMEHA_ATTACKED_3">
      <Text>Za moją gościnę odpłacasz mi zdradą! Widzę, że źle cię osądziłem i źle odczytałem twoje zamiary.</Text>
    </Row>
    <Row Tag="TXT_KEY_LEADER_KAMEHAMEHA_DECLAREWAR_1">
      <Text>Starożytny ogień podróżujący po niebie zapowiedział ten dzień, ale w swej głupocie wierzyłem, że będzie inaczej. Przygotuj się na zniszczenie, choć żyliśmy w przyjaźni.</Text>
    </Row>
    <Row Tag="TXT_KEY_LEADER_KAMEHAMEHA_DECLAREWAR_2">
      <Text>Udało mi się dźwignąć kamień Naha, a jednak mimo to stajesz przeciwko mnie. Przepowiednia głosi, że zjednoczę te ziemie, a ty stoisz na mej drodze.</Text>
    </Row>
    <Row Tag="TXT_KEY_LEADER_KAMEHAMEHA_DECLAREWAR_3">
      <Text>Prawa strzaskanego wiosła po raz ostatni zostały złamane. Podobnie jak ojciec płacze, dyscyplinując swe dziecię, tak i ja będę płakał, niszcząc twój naród.</Text>
    </Row>
    <Row Tag="TXT_KEY_LEADER_KAMEHAMEHA_DEFEATED_1">
      <Text>Gwiazdy przepowiadały, że będę „zabójcą wodzów”. Nie takiego końca się spodziewałem, ale przepowiednia musi się wypełnić.</Text>
    </Row>
    <Row Tag="TXT_KEY_LEADER_KAMEHAMEHA_DEFEATED_2">
      <Text>Moi ludzie napiszą hula o twym zwycięstwie. Może pewnego dnia zrozumiemy, czemu bogowie nas opuścili.</Text>
    </Row>
    <Row Tag="TXT_KEY_LEADER_KAMEHAMEHA_DEFEATED_3">
      <Text>Krab o twardej skorupie ustępuje, lud komety gaśnie. Kanaloa przybył po mnie.</Text>
    </Row>
    <Row Tag="TXT_KEY_LEADER_KAMEHAMEHA_DEMANDTRIBUTE_ANGRY">
      <Text>Potrzebna jest mała składka od wszystkich z okazji nadchodzącej uczty!</Text>
    </Row>
    <Row Tag="TXT_KEY_LEADER_KAMEHAMEHA_DEMANDTRIBUTE_HAPPY">
      <Text>Nie dostałem twojej składki na występy hula.</Text>
    </Row>
    <Row Tag="TXT_KEY_LEADER_KAMEHAMEHA_DEMANDTRIBUTE_NEUTRAL">
      <Text>Potrzebna nam twa przyjacielska pomoc!</Text>
    </Row>
    <Row Tag="TXT_KEY_LEADER_KAMEHAMEHA_DISAGREE_SHORT_1">
      <Text>Nie, to wykluczone.</Text>
    </Row>
    <Row Tag="TXT_KEY_LEADER_KAMEHAMEHA_DISAGREE_SHORT_2">
      <Text>Odmawiam.</Text>
    </Row>
    <Row Tag="TXT_KEY_LEADER_KAMEHAMEHA_DISAGREE_SHORT_3">
      <Text>Absolutnie nie.</Text>
    </Row>
    <Row Tag="TXT_KEY_LEADER_KAMEHAMEHA_DISAGREE_SHORT_4">
      <Text>To nie do przyjęcia.</Text>
    </Row>
    <Row Tag="TXT_KEY_LEADER_KAMEHAMEHA_DISAGREE_SHORT_5">
      <Text>Oczywiście nic z tego.</Text>
    </Row>
    <Row Tag="TXT_KEY_LEADER_KAMEHAMEHA_DISAGREE_SHORT_6">
      <Text>To nie do przyjęcia.</Text>
    </Row>
    <Row Tag="TXT_KEY_LEADER_KAMEHAMEHA_DISAGREE_SHORT_7">
      <Text>Nie mówisz chyba poważnie!</Text>
    </Row>
    <Row Tag="TXT_KEY_LEADER_KAMEHAMEHA_FIRSTGREETING_1">
      <Text>Ach, przyjaciel odkrywca! Witamy na wielkich wyspach polinezyjskich! Ja, wielki król Polinezji, zapraszam cię do mych ognisk i stołów.</Text>
    </Row>
    <Row Tag="TXT_KEY_LEADER_KAMEHAMEHA_FIRSTGREETING_2">
      <Text>Witaj, nowa twarzy! Jestem Kamehameha, król Polinezji. Chodź, musimy zorganizować wielkie przyjęcie, aby uczcić to spotkanie.</Text>
    </Row>
    <Row Tag="TXT_KEY_LEADER_KAMEHAMEHA_FIRSTGREETING_3">
      <Text>Witaj i bądź zdrów. Jestem Kamehameha, wielki król Polinezji. Podzielmy się swymi surowcami i żyjmy w harmonii!</Text>
    </Row>
    <Row Tag="TXT_KEY_LEADER_KAMEHAMEHA_GOODBYE_1">
      <Text>Do następnego spotkania.</Text>
    </Row>
    <Row Tag="TXT_KEY_LEADER_KAMEHAMEHA_GOODBYE_2">
      <Text>Bywaj.</Text>
    </Row>
    <Row Tag="TXT_KEY_LEADER_KAMEHAMEHA_GOODBYE_3">
      <Text>Żegnaj.</Text>
    </Row>
    <Row Tag="TXT_KEY_LEADER_KAMEHAMEHA_GOODBYE_4">
      <Text>Bywaj.</Text>
    </Row>
    <Row Tag="TXT_KEY_LEADER_KAMEHAMEHA_GOODBYE_5">
      <Text>To wszystko.</Text>
    </Row>
    <Row Tag="TXT_KEY_LEADER_KAMEHAMEHA_GOODBYE_6">
      <Text>Możesz odejść.</Text>
    </Row>
    <Row Tag="TXT_KEY_LEADER_KAMEHAMEHA_GREETING_1">
      <Text>Miłego dnia.</Text>
    </Row>
    <Row Tag="TXT_KEY_LEADER_KAMEHAMEHA_GREETING_2">
      <Text>Pozdrawiam cię.</Text>
    </Row>
    <Row Tag="TXT_KEY_LEADER_KAMEHAMEHA_GREETING_3">
      <Text>Witaj.</Text>
    </Row>
    <Row Tag="TXT_KEY_LEADER_KAMEHAMEHA_GREETING_4">
      <Text>Zawsze miło cię widzieć.</Text>
    </Row>
    <Row Tag="TXT_KEY_LEADER_KAMEHAMEHA_GREETING_5">
      <Text>Tak?</Text>
    </Row>
    <Row Tag="TXT_KEY_LEADER_KAMEHAMEHA_GREETING_6">
      <Text>Czego chcesz?</Text>
    </Row>
    <Row Tag="TXT_KEY_LEADER_KAMEHAMEHA_LETSHEARIT_1">
      <Text>Wysłucham cię.</Text>
    </Row>
    <Row Tag="TXT_KEY_LEADER_KAMEHAMEHA_LETSHEARIT_2">
      <Text>Mów.</Text>
    </Row>
    <Row Tag="TXT_KEY_LEADER_KAMEHAMEHA_LETSHEARIT_3">
      <Text>Kontynuuj.</Text>
    </Row>
    <Row Tag="TXT_KEY_LEADER_KAMEHAMEHA_LETSHEARIT_4">
      <Text>Słucham.</Text>
    </Row>
    <Row Tag="TXT_KEY_LEADER_KAMEHAMEHA_LETSHEARIT_5">
      <Text>Tak?</Text>
    </Row>
    <Row Tag="TXT_KEY_LEADER_KAMEHAMEHA_LOSEWAR_1">
      <Text>Może jednak gwiazdy się myliły... Muszę skonsultować się z moimi kahunami.</Text>
    </Row>
    <Row Tag="TXT_KEY_LEADER_KAMEHAMEHA_LOSEWAR_2">
      <Text>Pele zaszczyciła cię swoim tańcem. Udało ci się zdobyć jej względy, ale nie licz na nie zbyt długo.</Text>
    </Row>
    <Row Tag="TXT_KEY_LEADER_KAMEHAMEHA_TRADE_NEEDMORE_ANGRY_1">
      <Text>Doprawdy nie rozumiem, dlaczego chcesz mnie oszukać. Popraw, proszę, swoją ofertę.</Text>
    </Row>
    <Row Tag="TXT_KEY_LEADER_KAMEHAMEHA_TRADE_NEEDMORE_ANGRY_2">
      <Text>Niestety, to nie wystarczy.</Text>
    </Row>
    <Row Tag="TXT_KEY_LEADER_KAMEHAMEHA_TRADE_NEEDMORE_ANGRY_3">
      <Text>Musisz się bardziej postarać.</Text>
    </Row>
    <Row Tag="TXT_KEY_LEADER_KAMEHAMEHA_TRADE_NEEDMORE_ANGRY_4">
      <Text>Prawie...</Text>
    </Row>
    <Row Tag="TXT_KEY_LEADER_KAMEHAMEHA_TRADE_NEEDMORE_HAPPY_1">
      <Text>Jesteś dla mnie jak członek rodziny, ale nawet rodzina nie może być tak impertynencka.</Text>
    </Row>
    <Row Tag="TXT_KEY_LEADER_KAMEHAMEHA_TRADE_NEEDMORE_HAPPY_2">
      <Text>To wszystko, na co cię stać?</Text>
    </Row>
    <Row Tag="TXT_KEY_LEADER_KAMEHAMEHA_TRADE_NEEDMORE_HAPPY_3">
      <Text>Prawie dobiliśmy targu...</Text>
    </Row>
    <Row Tag="TXT_KEY_LEADER_KAMEHAMEHA_TRADE_NEEDMORE_NEUTRAL_1">
      <Text>Cenię sobie dobre intencje, ale musisz się postarać o lepszą ofertę.</Text>
    </Row>
    <Row Tag="TXT_KEY_LEADER_KAMEHAMEHA_TRADE_NEEDMORE_NEUTRAL_2">
      <Text>To nie wystarczy.</Text>
    </Row>
    <Row Tag="TXT_KEY_LEADER_KAMEHAMEHA_TRADE_NEEDMORE_NEUTRAL_3">
      <Text>Prawie...</Text>
    </Row>
    <Row Tag="TXT_KEY_LEADER_KAMEHAMEHA_TRADE_NO_ANGRY">
      <Text>Czy chcesz mi sprowadzić kahunów na głowę? To nie wystarczy.</Text>
    </Row>
    <Row Tag="TXT_KEY_LEADER_KAMEHAMEHA_TRADE_NO_HAPPY">
      <Text>Tysiąckrotne dzięki, ale nie.</Text>
    </Row>
    <Row Tag="TXT_KEY_LEADER_KAMEHAMEHA_TRADE_NO_NEUTRAL">
      <Text>Nie jestem zainteresowany.</Text>
    </Row>
    <Row Tag="TXT_KEY_LEADER_KAMEHAMEHA_TRADE_YES_ANGRY">
      <Text>Zgoda.</Text>
    </Row>
    <Row Tag="TXT_KEY_LEADER_KAMEHAMEHA_TRADE_YES_HAPPY">
      <Text>Ależ oczywiście! Proszę!</Text>
    </Row>
    <Row Tag="TXT_KEY_LEADER_KAMEHAMEHA_TRADE_YES_NEUTRAL">
      <Text>Jak najbardziej!</Text>
    </Row>
    <Row Tag="TXT_KEY_LEADER_KAMEHAMEHA_TRADEREQUEST_ANGRY">
      <Text>Mieliśmy burzliwą historię, ale może czas zacząć się dogadywać.</Text>
    </Row>
    <Row Tag="TXT_KEY_LEADER_KAMEHAMEHA_TRADEREQUEST_HAPPY">
      <Text>Chodź, niech nasze ludy świętują razem!</Text>
    </Row>
    <Row Tag="TXT_KEY_LEADER_KAMEHAMEHA_TRADEREQUEST_NEUTRAL">
      <Text>Może uznasz tę umowę za tak korzystną, jaką jest ona dla mnie?</Text>
    </Row>
    <Row Tag="TXT_KEY_LEADER_KAMEHAMEHA_TRIBUTE_NO_ANGRY">
      <Text>Kahuni zażądaliby mojej głowy, gdybym się na coś podobnego zgodził.</Text>
    </Row>
    <Row Tag="TXT_KEY_LEADER_KAMEHAMEHA_TRIBUTE_NO_HAPPY">
      <Text>Widzę, że dzisiejszy dzień jest jednym wielkim żartem!</Text>
    </Row>
    <Row Tag="TXT_KEY_LEADER_KAMEHAMEHA_TRIBUTE_NO_NEUTRAL">
      <Text>Obawiam się, że nie mam niczego do oddania. Będę musiał odprawić cię z pustymi rękoma.</Text>
    </Row>
    <Row Tag="TXT_KEY_LEADER_KAMEHAMEHA_TRIBUTE_YES_ANGRY">
      <Text>Gwiazdy mówią mi, że powinienem się zgodzić, choć nie rozumiem ich motywów.</Text>
    </Row>
    <Row Tag="TXT_KEY_LEADER_KAMEHAMEHA_TRIBUTE_YES_HAPPY">
      <Text>Oczywiście! Bo przecież po co ma się przyjaciół, jeśli nie po to, by dzielić się z nimi bogactwem?</Text>
    </Row>
    <Row Tag="TXT_KEY_LEADER_KAMEHAMEHA_TRIBUTE_YES_NEUTRAL">
      <Text>Choć wolałbym grzeczniejszą prośbę, to zawsze miło się dzielić swym bogactwem.</Text>
    </Row>
    <Row Tag="TXT_KEY_LEADER_KAMEHAMEHA_WARBLUFF_1">
      <Text>Może innym razem.</Text>
    </Row>
    <Row Tag="TXT_KEY_LEADER_KAMEHAMEHA_WARBLUFF_2">
      <Text>Uważaj, po czym stąpasz.</Text>
    </Row>
    <Row Tag="TXT_KEY_LEADER_KAMEHAMEHA_WARBLUFF_3">
      <Text>Masz więcej rozumu, niż moi kahuni byli gotowi ci przyznać.</Text>
    </Row>
    <Row Tag="TXT_KEY_LEADER_KAMEHAMEHA_WINWAR_1">
      <Text>Wielki bóg Ku zasiadł ze mną do dysputy. Jego wola została ubrana w słowa: zakończmy nasze waśnie i nie denerwujmy go więcej.</Text>
    </Row>
    <Row Tag="TXT_KEY_LEADER_KAMEHAMEHA_WINWAR_2">
      <Text>Naprawdę zamiarem twoim było pokonanie polinezyjskiego ludu komety? W przyszłości lepiej skonsultuj się ze swymi kahunami przed podjęciem podobnie głupich decyzji.</Text>
    </Row>
  </Language_PL_PL>
</GameData>